pipeline_parallel/__init__.py
pipeline_parallel/arg_list.py
pipeline_parallel/fake_server.py
pipeline_parallel/process_pool.py
pipeline_parallel/utils.py
pipeline_parallel-1.3.1.data/data/*/README.adoc
pipeline_parallel-1.3.1.dist-info/LICENSE.txt
pipeline_parallel-1.3.1.dist-info/METADATA
pipeline_parallel-1.3.1.dist-info/WHEEL
pipeline_parallel-1.3.1.dist-info/top_level.txt
pipeline_parallel-1.3.1.dist-info/RECORD
