Metadata-Version: 2.1
Name: pipeline-parallel
Version: 1.3.1
Summary: "To run processes in parallel by managing CPU and RAM. Initially designed for JWST pipeline"
Home-page: https://gitlab.com/jwst_fr/pipeline_parallel
Author: "Christophe Cossou"
Author-email: "ccossou@gmail.com"
License: UNKNOWN
Platform: ["Linux"
Platform: "Mac OS X"]
Requires-Python: >=3.7
Requires-Dist: astropy
Requires-Dist: psutil
Requires-Dist: numpy
Requires-Dist: pytest
